{
  "callees_count": 2,
  "callers_count": 2,
  "comment_regular": "",
  "comment_repeatable": "",
  "data_refs_count": 2,
  "display_name": "NiNIFImageReader::NiNIFImageReader(void)",
  "end_ea": "0x7339B5",
  "flags": 20480,
  "has_pseudocode": true,
  "name": "??0NiNIFImageReader@@QAE@XZ",
  "segment": ".text",
  "sha256": "06cd09979c5220c027db1cc6612c9d3e0d61cbbcf21b22d12cd37f5461d5228d",
  "size": 117,
  "start_ea": "0x733940",
  "type": "NiNIFImageReader *__thiscall(NiNIFImageReader *__hidden this)",
  "xrefs_from_count": 33,
  "xrefs_to_count": 2
}