{
  "decl": "NMDATETIMEWMKEYDOWNW",
  "kind": "struct",
  "members": [
    {
      "name": "nmhdr",
      "offset_bits": 0,
      "offset_bytes": 0,
      "size_bits": 192,
      "type": "NMHDR"
    },
    {
      "name": "nVirtKey",
      "offset_bits": 192,
      "offset_bytes": 24,
      "size_bits": 32,
      "type": "int"
    },
    {
      "name": "pszFormat",
      "offset_bits": 224,
      "offset_bytes": 28,
      "size_bits": 32,
      "type": "LPCWSTR"
    },
    {
      "name": "st",
      "offset_bits": 256,
      "offset_bytes": 32,
      "size_bits": 128,
      "type": "SYSTEMTIME"
    }
  ],
  "name": "NMDATETIMEWMKEYDOWNW",
  "ordinal": 6387,
  "properties": {
    "is_array": false,
    "is_decl_typedef": true,
    "is_enum": false,
    "is_func": false,
    "is_ptr": false,
    "is_scalar": false,
    "is_struct": true,
    "is_union": false,
    "is_void": false
  }
}