[
  {
    "from_ea": "0x994408",
    "to_ea": "0x99440C",
    "to_name": "",
    "type": 21
  },
  {
    "from_ea": "0x99440C",
    "to_ea": "0x994410",
    "to_name": "",
    "type": 21
  },
  {
    "from_ea": "0x994410",
    "to_ea": "0x994418",
    "to_name": "",
    "type": 21
  },
  {
    "from_ea": "0x994410",
    "to_ea": "0xAAB960",
    "to_name": "xmmword_AAB960",
    "type": 3
  },
  {
    "from_ea": "0x994418",
    "to_ea": "0x99441D",
    "to_name": "",
    "type": 21
  },
  {
    "from_ea": "0x99441D",
    "to_ea": "0x994422",
    "to_name": "",
    "type": 21
  },
  {
    "from_ea": "0x994422",
    "to_ea": "0x994426",
    "to_name": "",
    "type": 21
  },
  {
    "from_ea": "0x994426",
    "to_ea": "0x99442B",
    "to_name": "",
    "type": 21
  },
  {
    "from_ea": "0x99442B",
    "to_ea": "0x99442E",
    "to_name": "",
    "type": 21
  },
  {
    "from_ea": "0x99442E",
    "to_ea": "0x994433",
    "to_name": "",
    "type": 21
  },
  {
    "from_ea": "0x994433",
    "to_ea": "0x99443C",
    "to_name": "",
    "type": 21
  },
  {
    "from_ea": "0x994433",
    "to_ea": "0xAA80B0",
    "to_name": "qword_AA80B0",
    "type": 3
  },
  {
    "from_ea": "0x99443C",
    "to_ea": "0x994445",
    "to_name": "",
    "type": 21
  },
  {
    "from_ea": "0x99443C",
    "to_ea": "0xAA80B0",
    "to_name": "qword_AA80B0",
    "type": 3
  },
  {
    "from_ea": "0x994445",
    "to_ea": "0x994447",
    "to_name": "",
    "type": 21
  },
  {
    "from_ea": "0x994447",
    "to_ea": "0x994450",
    "to_name": "",
    "type": 21
  },
  {
    "from_ea": "0x994447",
    "to_ea": "0xAA84C0",
    "to_name": "xmmword_AA84C0",
    "type": 3
  },
  {
    "from_ea": "0x994450",
    "to_ea": "0x994455",
    "to_name": "",
    "type": 21
  },
  {
    "from_ea": "0x994455",
    "to_ea": "0x993FB6",
    "to_name": "__pow_pentium4:::BACK_MAIN",
    "type": 19
  }
]