[
  {
    "ea": "0x6A0800",
    "line": "push    0FFFFFFFFh",
    "mnemonic": "push",
    "size": 2
  },
  {
    "ea": "0x6A0802",
    "line": "push    offset MagicShaderHitEffect_constr_args_SEH",
    "mnemonic": "push",
    "size": 5
  },
  {
    "ea": "0x6A0807",
    "line": "mov     eax, large fs:0",
    "mnemonic": "mov",
    "size": 6
  },
  {
    "ea": "0x6A080D",
    "line": "push    eax",
    "mnemonic": "push",
    "size": 1
  },
  {
    "ea": "0x6A080E",
    "line": "push    ecx",
    "mnemonic": "push",
    "size": 1
  },
  {
    "ea": "0x6A080F",
    "line": "push    ebx",
    "mnemonic": "push",
    "size": 1
  },
  {
    "ea": "0x6A0810",
    "line": "push    ebp",
    "mnemonic": "push",
    "size": 1
  },
  {
    "ea": "0x6A0811",
    "line": "push    esi",
    "mnemonic": "push",
    "size": 1
  },
  {
    "ea": "0x6A0812",
    "line": "push    edi",
    "mnemonic": "push",
    "size": 1
  },
  {
    "ea": "0x6A0813",
    "line": "mov     eax, ds:0B30AACh",
    "mnemonic": "mov",
    "size": 5
  },
  {
    "ea": "0x6A0818",
    "line": "xor     eax, esp",
    "mnemonic": "xor",
    "size": 2
  },
  {
    "ea": "0x6A081A",
    "line": "push    eax",
    "mnemonic": "push",
    "size": 1
  },
  {
    "ea": "0x6A081B",
    "line": "lea     eax, [esp+24h+var_C]",
    "mnemonic": "lea",
    "size": 4
  },
  {
    "ea": "0x6A081F",
    "line": "mov     large fs:0, eax",
    "mnemonic": "mov",
    "size": 6
  },
  {
    "ea": "0x6A0825",
    "line": "mov     esi, ecx",
    "mnemonic": "mov",
    "size": 2
  },
  {
    "ea": "0x6A0827",
    "line": "mov     [esp+24h+var_10], esi",
    "mnemonic": "mov",
    "size": 4
  },
  {
    "ea": "0x6A082B",
    "line": "mov     edi, [esp+24h+arg_4]",
    "mnemonic": "mov",
    "size": 4
  },
  {
    "ea": "0x6A082F",
    "line": "mov     eax, [esp+24h+arg_0]",
    "mnemonic": "mov",
    "size": 4
  },
  {
    "ea": "0x6A0833",
    "line": "push    edi",
    "mnemonic": "push",
    "size": 1
  },
  {
    "ea": "0x6A0834",
    "line": "push    eax",
    "mnemonic": "push",
    "size": 1
  },
  {
    "ea": "0x6A0835",
    "line": "call    MagicHitEffect_constr_args",
    "mnemonic": "call",
    "size": 5
  },
  {
    "ea": "0x6A083A",
    "line": "xor     ebx, ebx",
    "mnemonic": "xor",
    "size": 2
  },
  {
    "ea": "0x6A083C",
    "line": "mov     dword ptr [esi], offset ??_7MagicShaderHitEffect@@6B@; const MagicShaderHitEffect::`vftable'",
    "mnemonic": "mov",
    "size": 6
  },
  {
    "ea": "0x6A0842",
    "line": "mov     [esp+24h+var_4], ebx",
    "mnemonic": "mov",
    "size": 4
  },
  {
    "ea": "0x6A0846",
    "line": "mov     [esi+3Ch], ebx",
    "mnemonic": "mov",
    "size": 3
  },
  {
    "ea": "0x6A0849",
    "line": "mov     [esi+40h], ebx",
    "mnemonic": "mov",
    "size": 3
  },
  {
    "ea": "0x6A084C",
    "line": "mov     [esi+48h], ebx",
    "mnemonic": "mov",
    "size": 3
  },
  {
    "ea": "0x6A084F",
    "line": "mov     [esi+34h], ebx",
    "mnemonic": "mov",
    "size": 3
  },
  {
    "ea": "0x6A0852",
    "line": "mov     ecx, [edi+8]",
    "mnemonic": "mov",
    "size": 3
  },
  {
    "ea": "0x6A0855",
    "line": "push    ebx",
    "mnemonic": "push",
    "size": 1
  },
  {
    "ea": "0x6A0856",
    "line": "mov     byte ptr [esp+28h+var_4], 3",
    "mnemonic": "mov",
    "size": 5
  },
  {
    "ea": "0x6A085B",
    "line": "call    MagicItem_GetFXEffect",
    "mnemonic": "call",
    "size": 5
  },
  {
    "ea": "0x6A0860",
    "line": "fldz",
    "mnemonic": "fldz",
    "size": 2
  },
  {
    "ea": "0x6A0862",
    "line": "mov     ecx, [eax+78h]",
    "mnemonic": "mov",
    "size": 3
  },
  {
    "ea": "0x6A0865",
    "line": "fstp    dword ptr [esi+38h]",
    "mnemonic": "fstp",
    "size": 3
  },
  {
    "ea": "0x6A0868",
    "line": "mov     ebp, ds:0A2807Ch",
    "mnemonic": "mov",
    "size": 6
  },
  {
    "ea": "0x6A086E",
    "line": "mov     [esi+34h], ecx",
    "mnemonic": "mov",
    "size": 3
  },
  {
    "ea": "0x6A0871",
    "line": "mov     edi, [esi+48h]",
    "mnemonic": "mov",
    "size": 3
  },
  {
    "ea": "0x6A0874",
    "line": "cmp     edi, ebx",
    "mnemonic": "cmp",
    "size": 2
  },
  {
    "ea": "0x6A0876",
    "line": "jz      short loc_6A0893",
    "mnemonic": "jz",
    "size": 2
  },
  {
    "ea": "0x6A0878",
    "line": "lea     edx, [edi+4]",
    "mnemonic": "lea",
    "size": 3
  },
  {
    "ea": "0x6A087B",
    "line": "push    edx; lpAddend",
    "mnemonic": "push",
    "size": 1
  },
  {
    "ea": "0x6A087C",
    "line": "call    ebp ; InterlockedDecrement",
    "mnemonic": "call",
    "size": 2
  },
  {
    "ea": "0x6A087E",
    "line": "test    eax, eax",
    "mnemonic": "test",
    "size": 2
  },
  {
    "ea": "0x6A0880",
    "line": "jnz     short loc_6A0890",
    "mnemonic": "jnz",
    "size": 2
  },
  {
    "ea": "0x6A0882",
    "line": "cmp     edi, ebx",
    "mnemonic": "cmp",
    "size": 2
  },
  {
    "ea": "0x6A0884",
    "line": "jz      short loc_6A0890",
    "mnemonic": "jz",
    "size": 2
  },
  {
    "ea": "0x6A0886",
    "line": "mov     eax, [edi]",
    "mnemonic": "mov",
    "size": 2
  },
  {
    "ea": "0x6A0888",
    "line": "mov     edx, [eax]",
    "mnemonic": "mov",
    "size": 2
  },
  {
    "ea": "0x6A088A",
    "line": "push    1",
    "mnemonic": "push",
    "size": 2
  },
  {
    "ea": "0x6A088C",
    "line": "mov     ecx, edi",
    "mnemonic": "mov",
    "size": 2
  },
  {
    "ea": "0x6A088E",
    "line": "call    edx",
    "mnemonic": "call",
    "size": 2
  },
  {
    "ea": "0x6A0890",
    "line": "mov     [esi+48h], ebx",
    "mnemonic": "mov",
    "size": 3
  },
  {
    "ea": "0x6A0893",
    "line": "mov     edi, [esi+3Ch]",
    "mnemonic": "mov",
    "size": 3
  },
  {
    "ea": "0x6A0896",
    "line": "cmp     edi, ebx",
    "mnemonic": "cmp",
    "size": 2
  },
  {
    "ea": "0x6A0898",
    "line": "jz      short loc_6A08B5",
    "mnemonic": "jz",
    "size": 2
  },
  {
    "ea": "0x6A089A",
    "line": "lea     eax, [edi+4]",
    "mnemonic": "lea",
    "size": 3
  },
  {
    "ea": "0x6A089D",
    "line": "push    eax; lpAddend",
    "mnemonic": "push",
    "size": 1
  },
  {
    "ea": "0x6A089E",
    "line": "call    ebp ; InterlockedDecrement",
    "mnemonic": "call",
    "size": 2
  },
  {
    "ea": "0x6A08A0",
    "line": "test    eax, eax",
    "mnemonic": "test",
    "size": 2
  },
  {
    "ea": "0x6A08A2",
    "line": "jnz     short loc_6A08B2",
    "mnemonic": "jnz",
    "size": 2
  },
  {
    "ea": "0x6A08A4",
    "line": "cmp     edi, ebx",
    "mnemonic": "cmp",
    "size": 2
  },
  {
    "ea": "0x6A08A6",
    "line": "jz      short loc_6A08B2",
    "mnemonic": "jz",
    "size": 2
  },
  {
    "ea": "0x6A08A8",
    "line": "mov     edx, [edi]",
    "mnemonic": "mov",
    "size": 2
  },
  {
    "ea": "0x6A08AA",
    "line": "mov     eax, [edx]",
    "mnemonic": "mov",
    "size": 2
  },
  {
    "ea": "0x6A08AC",
    "line": "push    1",
    "mnemonic": "push",
    "size": 2
  },
  {
    "ea": "0x6A08AE",
    "line": "mov     ecx, edi",
    "mnemonic": "mov",
    "size": 2
  },
  {
    "ea": "0x6A08B0",
    "line": "call    eax",
    "mnemonic": "call",
    "size": 2
  },
  {
    "ea": "0x6A08B2",
    "line": "mov     [esi+3Ch], ebx",
    "mnemonic": "mov",
    "size": 3
  },
  {
    "ea": "0x6A08B5",
    "line": "mov     edi, [esi+40h]",
    "mnemonic": "mov",
    "size": 3
  },
  {
    "ea": "0x6A08B8",
    "line": "cmp     edi, ebx",
    "mnemonic": "cmp",
    "size": 2
  },
  {
    "ea": "0x6A08BA",
    "line": "jz      short loc_6A08D7",
    "mnemonic": "jz",
    "size": 2
  },
  {
    "ea": "0x6A08BC",
    "line": "lea     ecx, [edi+4]",
    "mnemonic": "lea",
    "size": 3
  },
  {
    "ea": "0x6A08BF",
    "line": "push    ecx; lpAddend",
    "mnemonic": "push",
    "size": 1
  },
  {
    "ea": "0x6A08C0",
    "line": "call    ebp ; InterlockedDecrement",
    "mnemonic": "call",
    "size": 2
  },
  {
    "ea": "0x6A08C2",
    "line": "test    eax, eax",
    "mnemonic": "test",
    "size": 2
  },
  {
    "ea": "0x6A08C4",
    "line": "jnz     short loc_6A08D4",
    "mnemonic": "jnz",
    "size": 2
  },
  {
    "ea": "0x6A08C6",
    "line": "cmp     edi, ebx",
    "mnemonic": "cmp",
    "size": 2
  },
  {
    "ea": "0x6A08C8",
    "line": "jz      short loc_6A08D4",
    "mnemonic": "jz",
    "size": 2
  },
  {
    "ea": "0x6A08CA",
    "line": "mov     edx, [edi]",
    "mnemonic": "mov",
    "size": 2
  },
  {
    "ea": "0x6A08CC",
    "line": "mov     eax, [edx]",
    "mnemonic": "mov",
    "size": 2
  },
  {
    "ea": "0x6A08CE",
    "line": "push    1",
    "mnemonic": "push",
    "size": 2
  },
  {
    "ea": "0x6A08D0",
    "line": "mov     ecx, edi",
    "mnemonic": "mov",
    "size": 2
  },
  {
    "ea": "0x6A08D2",
    "line": "call    eax",
    "mnemonic": "call",
    "size": 2
  },
  {
    "ea": "0x6A08D4",
    "line": "mov     [esi+40h], ebx",
    "mnemonic": "mov",
    "size": 3
  },
  {
    "ea": "0x6A08D7",
    "line": "mov     ecx, [esi+18h]",
    "mnemonic": "mov",
    "size": 3
  },
  {
    "ea": "0x6A08DA",
    "line": "mov     [esi+28h], bl",
    "mnemonic": "mov",
    "size": 3
  },
  {
    "ea": "0x6A08DD",
    "line": "mov     edx, [ecx+0Ch]",
    "mnemonic": "mov",
    "size": 3
  },
  {
    "ea": "0x6A08E0",
    "line": "mov     eax, [edx+1Ch]",
    "mnemonic": "mov",
    "size": 3
  },
  {
    "ea": "0x6A08E3",
    "line": "mov     ecx, [eax+98h]",
    "mnemonic": "mov",
    "size": 6
  },
  {
    "ea": "0x6A08E9",
    "line": "mov     [esi+2Ch], ecx",
    "mnemonic": "mov",
    "size": 3
  },
  {
    "ea": "0x6A08EC",
    "line": "mov     [esi+30h], ebx",
    "mnemonic": "mov",
    "size": 3
  },
  {
    "ea": "0x6A08EF",
    "line": "mov     ecx, ds:0B333C4h",
    "mnemonic": "mov",
    "size": 6
  },
  {
    "ea": "0x6A08F5",
    "line": "cmp     [esi+1Ch], ecx",
    "mnemonic": "cmp",
    "size": 3
  },
  {
    "ea": "0x6A08F8",
    "line": "jnz     short loc_6A0927",
    "mnemonic": "jnz",
    "size": 2
  },
  {
    "ea": "0x6A08FA",
    "line": "push    ebx",
    "mnemonic": "push",
    "size": 1
  },
  {
    "ea": "0x6A08FB",
    "line": "call    PlayerCharacter_GetPlayerNode",
    "mnemonic": "call",
    "size": 5
  },
  {
    "ea": "0x6A0900",
    "line": "test    eax, eax",
    "mnemonic": "test",
    "size": 2
  },
  {
    "ea": "0x6A0902",
    "line": "jz      short loc_6A0920",
    "mnemonic": "jz",
    "size": 2
  },
  {
    "ea": "0x6A0904",
    "line": "mov     ecx, ds:0B333C4h",
    "mnemonic": "mov",
    "size": 6
  },
  {
    "ea": "0x6A090A",
    "line": "push    ebx",
    "mnemonic": "push",
    "size": 1
  },
  {
    "ea": "0x6A090B",
    "line": "call    PlayerCharacter_GetPlayerNode",
    "mnemonic": "call",
    "size": 5
  },
  {
    "ea": "0x6A0910",
    "line": "test    byte ptr [eax+18h], 1",
    "mnemonic": "test",
    "size": 4
  },
  {
    "ea": "0x6A0914",
    "line": "jnz     short loc_6A0920",
    "mnemonic": "jnz",
    "size": 2
  },
  {
    "ea": "0x6A0916",
    "line": "mov     eax, 1",
    "mnemonic": "mov",
    "size": 5
  },
  {
    "ea": "0x6A091B",
    "line": "mov     [esi+44h], al",
    "mnemonic": "mov",
    "size": 3
  },
  {
    "ea": "0x6A091E",
    "line": "jmp     short loc_6A092A",
    "mnemonic": "jmp",
    "size": 2
  },
  {
    "ea": "0x6A0920",
    "line": "xor     eax, eax",
    "mnemonic": "xor",
    "size": 2
  },
  {
    "ea": "0x6A0922",
    "line": "mov     [esi+44h], al",
    "mnemonic": "mov",
    "size": 3
  },
  {
    "ea": "0x6A0925",
    "line": "jmp     short loc_6A092A",
    "mnemonic": "jmp",
    "size": 2
  },
  {
    "ea": "0x6A0927",
    "line": "mov     [esi+44h], bl",
    "mnemonic": "mov",
    "size": 3
  },
  {
    "ea": "0x6A092A",
    "line": "cmp     dword ptr [esi+2Ch], 52414944h",
    "mnemonic": "cmp",
    "size": 7
  },
  {
    "ea": "0x6A0931",
    "line": "jnz     short loc_6A095C",
    "mnemonic": "jnz",
    "size": 2
  },
  {
    "ea": "0x6A0933",
    "line": "mov     eax, [esi+18h]",
    "mnemonic": "mov",
    "size": 3
  },
  {
    "ea": "0x6A0936",
    "line": "push    ebx; int",
    "mnemonic": "push",
    "size": 1
  },
  {
    "ea": "0x6A0937",
    "line": "push    offset ??_R0?AVDisintegrateArmorEffect@@@8; struct TypeDescriptor *",
    "mnemonic": "push",
    "size": 5
  },
  {
    "ea": "0x6A093C",
    "line": "push    offset ??_R0?AVActiveEffect@@@8; struct _s_RTTICompleteObjectLocator *",
    "mnemonic": "push",
    "size": 5
  },
  {
    "ea": "0x6A0941",
    "line": "push    ebx; int",
    "mnemonic": "push",
    "size": 1
  },
  {
    "ea": "0x6A0942",
    "line": "push    eax; void *",
    "mnemonic": "push",
    "size": 1
  },
  {
    "ea": "0x6A0943",
    "line": "call    OblivionDynamicCast",
    "mnemonic": "call",
    "size": 5
  },
  {
    "ea": "0x6A0948",
    "line": "add     esp, 14h",
    "mnemonic": "add",
    "size": 3
  },
  {
    "ea": "0x6A094B",
    "line": "cmp     eax, ebx",
    "mnemonic": "cmp",
    "size": 2
  },
  {
    "ea": "0x6A094D",
    "line": "jz      short loc_6A095C",
    "mnemonic": "jz",
    "size": 2
  },
  {
    "ea": "0x6A094F",
    "line": "mov     eax, [eax+38h]",
    "mnemonic": "mov",
    "size": 3
  },
  {
    "ea": "0x6A0952",
    "line": "cmp     eax, ebx",
    "mnemonic": "cmp",
    "size": 2
  },
  {
    "ea": "0x6A0954",
    "line": "jz      short loc_6A095C",
    "mnemonic": "jz",
    "size": 2
  },
  {
    "ea": "0x6A0956",
    "line": "mov     edx, [eax+8]",
    "mnemonic": "mov",
    "size": 3
  },
  {
    "ea": "0x6A0959",
    "line": "mov     [esi+30h], edx",
    "mnemonic": "mov",
    "size": 3
  },
  {
    "ea": "0x6A095C",
    "line": "mov     eax, esi",
    "mnemonic": "mov",
    "size": 2
  },
  {
    "ea": "0x6A095E",
    "line": "mov     ecx, dword ptr [esp+24h+var_C]",
    "mnemonic": "mov",
    "size": 4
  },
  {
    "ea": "0x6A0962",
    "line": "mov     large fs:0, ecx",
    "mnemonic": "mov",
    "size": 7
  },
  {
    "ea": "0x6A0969",
    "line": "pop     ecx",
    "mnemonic": "pop",
    "size": 1
  },
  {
    "ea": "0x6A096A",
    "line": "pop     edi",
    "mnemonic": "pop",
    "size": 1
  },
  {
    "ea": "0x6A096B",
    "line": "pop     esi",
    "mnemonic": "pop",
    "size": 1
  },
  {
    "ea": "0x6A096C",
    "line": "pop     ebp",
    "mnemonic": "pop",
    "size": 1
  },
  {
    "ea": "0x6A096D",
    "line": "pop     ebx",
    "mnemonic": "pop",
    "size": 1
  },
  {
    "ea": "0x6A096E",
    "line": "add     esp, 10h",
    "mnemonic": "add",
    "size": 3
  },
  {
    "ea": "0x6A0971",
    "line": "retn    8",
    "mnemonic": "retn",
    "size": 3
  }
]