[
  {
    "call_site_ea": "0x6943C8",
    "display_name": "LightEffect_PostLink",
    "function_ea": "0x6943C0",
    "name": "LightEffect_PostLink"
  },
  {
    "call_site_ea": "0x6A437A",
    "display_name": "ReanimateEffect_PostLink",
    "function_ea": "0x6A4370",
    "name": "ReanimateEffect_PostLink"
  },
  {
    "call_site_ea": "0x6A6D18",
    "display_name": "SunDamageEffect_PostLink",
    "function_ea": "0x6A6D10",
    "name": "SunDamageEffect_PostLink"
  },
  {
    "call_site_ea": "0x6A8628",
    "display_name": "ValueModifierEffect_PostLink",
    "function_ea": "0x6A8620",
    "name": "ValueModifierEffect_PostLink"
  }
]