[
  {
    "site_ea": "0x4106E6",
    "target_ea": "0xA28330",
    "target_name": "_BinkWait@4",
    "xref_type": 17
  },
  {
    "site_ea": "0x4106E6",
    "target_ea": "0xA28330",
    "target_name": "_BinkWait@4",
    "xref_type": 3
  },
  {
    "site_ea": "0x410715",
    "target_ea": "0xA319BC",
    "target_name": "aBinkPlaybackSk",
    "xref_type": 1
  },
  {
    "site_ea": "0x410726",
    "target_ea": "0xA28334",
    "target_name": "_BinkNextFrame@4",
    "xref_type": 17
  },
  {
    "site_ea": "0x410726",
    "target_ea": "0xA28334",
    "target_name": "_BinkNextFrame@4",
    "xref_type": 3
  },
  {
    "site_ea": "0x4107F9",
    "target_ea": "0xA280DC",
    "target_name": "Sleep",
    "xref_type": 17
  },
  {
    "site_ea": "0x4107F9",
    "target_ea": "0xA280DC",
    "target_name": "Sleep",
    "xref_type": 3
  }
]