[
  {
    "from_ea": "0x99626D",
    "to_ea": "0x996270",
    "to_name": "",
    "type": 21
  },
  {
    "from_ea": "0x996270",
    "to_ea": "0x996273",
    "to_name": "",
    "type": 21
  },
  {
    "from_ea": "0x996273",
    "to_ea": "0x996275",
    "to_name": "",
    "type": 21
  },
  {
    "from_ea": "0x996275",
    "to_ea": "0x996277",
    "to_name": "",
    "type": 21
  },
  {
    "from_ea": "0x996275",
    "to_ea": "0x99627C",
    "to_name": "loc_99627C",
    "type": 19
  },
  {
    "from_ea": "0x996277",
    "to_ea": "0x99627A",
    "to_name": "",
    "type": 21
  },
  {
    "from_ea": "0x99627A",
    "to_ea": "0x99628A",
    "to_name": "loc_99628A",
    "type": 19
  },
  {
    "from_ea": "0x99627C",
    "to_ea": "0x99627F",
    "to_name": "",
    "type": 21
  },
  {
    "from_ea": "0x99627F",
    "to_ea": "0x996282",
    "to_name": "",
    "type": 21
  },
  {
    "from_ea": "0x996282",
    "to_ea": "0x995CF8",
    "to_name": "__inc",
    "type": 17
  },
  {
    "from_ea": "0x996282",
    "to_ea": "0x996287",
    "to_name": "",
    "type": 21
  },
  {
    "from_ea": "0x996287",
    "to_ea": "0x99628A",
    "to_name": "loc_99628A",
    "type": 21
  },
  {
    "from_ea": "0x99628A",
    "to_ea": "0x99628E",
    "to_name": "",
    "type": 21
  },
  {
    "from_ea": "0x99628E",
    "to_ea": "0x9962D7",
    "to_name": "loc_9962D7",
    "type": 19
  },
  {
    "from_ea": "0x996290",
    "to_ea": "0x996293",
    "to_name": "",
    "type": 21
  },
  {
    "from_ea": "0x996293",
    "to_ea": "0x996296",
    "to_name": "",
    "type": 21
  },
  {
    "from_ea": "0x996296",
    "to_ea": "0x996298",
    "to_name": "",
    "type": 21
  },
  {
    "from_ea": "0x996298",
    "to_ea": "0x99629A",
    "to_name": "",
    "type": 21
  },
  {
    "from_ea": "0x996298",
    "to_ea": "0x9962E2",
    "to_name": "loc_9962E2",
    "type": 19
  },
  {
    "from_ea": "0x99629A",
    "to_ea": "0x99629D",
    "to_name": "",
    "type": 21
  },
  {
    "from_ea": "0x99629D",
    "to_ea": "0x9962A0",
    "to_name": "",
    "type": 21
  },
  {
    "from_ea": "0x9962A0",
    "to_ea": "0x9962A3",
    "to_name": "",
    "type": 21
  },
  {
    "from_ea": "0x9962A3",
    "to_ea": "0x9962A6",
    "to_name": "",
    "type": 21
  },
  {
    "from_ea": "0x9962A6",
    "to_ea": "0x9962A9",
    "to_name": "",
    "type": 21
  },
  {
    "from_ea": "0x9962A9",
    "to_ea": "0x9962AA",
    "to_name": "",
    "type": 21
  },
  {
    "from_ea": "0x9962AA",
    "to_ea": "0x9962AD",
    "to_name": "",
    "type": 21
  },
  {
    "from_ea": "0x9962AD",
    "to_ea": "0x9962AE",
    "to_name": "",
    "type": 21
  },
  {
    "from_ea": "0x9962AE",
    "to_ea": "0x9962AF",
    "to_name": "",
    "type": 21
  },
  {
    "from_ea": "0x9962AF",
    "to_ea": "0x9962B0",
    "to_name": "",
    "type": 21
  },
  {
    "from_ea": "0x9962B0",
    "to_ea": "0x9962B3",
    "to_name": "",
    "type": 21
  },
  {
    "from_ea": "0x9962B3",
    "to_ea": "0x9962B6",
    "to_name": "",
    "type": 21
  },
  {
    "from_ea": "0x9962B6",
    "to_ea": "0x995CA4",
    "to_name": "___check_float_string",
    "type": 17
  },
  {
    "from_ea": "0x9962B6",
    "to_ea": "0x9962BB",
    "to_name": "",
    "type": 21
  },
  {
    "from_ea": "0x9962BB",
    "to_ea": "0x9962BE",
    "to_name": "",
    "type": 21
  },
  {
    "from_ea": "0x9962BE",
    "to_ea": "0x9962C0",
    "to_name": "",
    "type": 21
  },
  {
    "from_ea": "0x9962C0",
    "to_ea": "0x9962C6",
    "to_name": "",
    "type": 21
  },
  {
    "from_ea": "0x9962C0",
    "to_ea": "0x996925",
    "to_name": "__input_l:::$error_return$25524",
    "type": 19
  },
  {
    "from_ea": "0x9962C6",
    "to_ea": "0x9962C9",
    "to_name": "",
    "type": 21
  },
  {
    "from_ea": "0x9962C9",
    "to_ea": "0x9962CC",
    "to_name": "",
    "type": 21
  },
  {
    "from_ea": "0x9962CC",
    "to_ea": "0x995CF8",
    "to_name": "__inc",
    "type": 17
  },
  {
    "from_ea": "0x9962CC",
    "to_ea": "0x9962D1",
    "to_name": "",
    "type": 21
  },
  {
    "from_ea": "0x9962D1",
    "to_ea": "0x9962D4",
    "to_name": "",
    "type": 21
  },
  {
    "from_ea": "0x9962D4",
    "to_ea": "0x9962D7",
    "to_name": "loc_9962D7",
    "type": 21
  },
  {
    "from_ea": "0x9962D7",
    "to_ea": "0x9962D8",
    "to_name": "",
    "type": 21
  },
  {
    "from_ea": "0x9962D8",
    "to_ea": "0x98506A",
    "to_name": "_isdigit",
    "type": 17
  },
  {
    "from_ea": "0x9962D8",
    "to_ea": "0x9962DD",
    "to_name": "",
    "type": 21
  },
  {
    "from_ea": "0x9962DD",
    "to_ea": "0x9962DF",
    "to_name": "",
    "type": 21
  },
  {
    "from_ea": "0x9962DF",
    "to_ea": "0x9962E0",
    "to_name": "",
    "type": 21
  },
  {
    "from_ea": "0x9962E0",
    "to_ea": "0x996290",
    "to_name": "loc_996290",
    "type": 19
  },
  {
    "from_ea": "0x9962E0",
    "to_ea": "0x9962E2",
    "to_name": "loc_9962E2",
    "type": 21
  },
  {
    "from_ea": "0x9962E2",
    "to_ea": "0x9962E5",
    "to_name": "",
    "type": 21
  },
  {
    "from_ea": "0x9962E5",
    "to_ea": "0x9962E9",
    "to_name": "",
    "type": 21
  },
  {
    "from_ea": "0x9962E9",
    "to_ea": "0x9962EB",
    "to_name": "",
    "type": 21
  },
  {
    "from_ea": "0x9962E9",
    "to_ea": "0x9962F8",
    "to_name": "loc_9962F8",
    "type": 19
  },
  {
    "from_ea": "0x9962EB",
    "to_ea": "0x9962EE",
    "to_name": "",
    "type": 21
  },
  {
    "from_ea": "0x9962EE",
    "to_ea": "0x9962F1",
    "to_name": "",
    "type": 21
  },
  {
    "from_ea": "0x9962F1",
    "to_ea": "0x9884D6",
    "to_name": "__ungetc_nolock",
    "type": 17
  },
  {
    "from_ea": "0x9962F1",
    "to_ea": "0x9962F6",
    "to_name": "",
    "type": 21
  },
  {
    "from_ea": "0x9962F6",
    "to_ea": "0x9962F7",
    "to_name": "",
    "type": 21
  },
  {
    "from_ea": "0x9962F7",
    "to_ea": "0x9962F8",
    "to_name": "loc_9962F8",
    "type": 21
  },
  {
    "from_ea": "0x9962F8",
    "to_ea": "0x9962FC",
    "to_name": "",
    "type": 21
  },
  {
    "from_ea": "0x9962FC",
    "to_ea": "0x996302",
    "to_name": "",
    "type": 21
  },
  {
    "from_ea": "0x9962FC",
    "to_ea": "0x996925",
    "to_name": "__input_l:::$error_return$25524",
    "type": 19
  },
  {
    "from_ea": "0x996302",
    "to_ea": "0x996306",
    "to_name": "",
    "type": 21
  },
  {
    "from_ea": "0x996306",
    "to_ea": "0x99630C",
    "to_name": "",
    "type": 21
  },
  {
    "from_ea": "0x996306",
    "to_ea": "0x99688D",
    "to_name": "loc_99688D",
    "type": 19
  },
  {
    "from_ea": "0x99630C",
    "to_ea": "0x99630F",
    "to_name": "",
    "type": 21
  },
  {
    "from_ea": "0x99630F",
    "to_ea": "0x996312",
    "to_name": "",
    "type": 21
  },
  {
    "from_ea": "0x996312",
    "to_ea": "0x996315",
    "to_name": "",
    "type": 21
  },
  {
    "from_ea": "0x996315",
    "to_ea": "0x996316",
    "to_name": "",
    "type": 21
  },
  {
    "from_ea": "0x996316",
    "to_ea": "0x996317",
    "to_name": "",
    "type": 21
  },
  {
    "from_ea": "0x996317",
    "to_ea": "0x99631A",
    "to_name": "",
    "type": 21
  },
  {
    "from_ea": "0x99631A",
    "to_ea": "0x99631E",
    "to_name": "",
    "type": 21
  },
  {
    "from_ea": "0x99631E",
    "to_ea": "0x996322",
    "to_name": "",
    "type": 21
  },
  {
    "from_ea": "0x996322",
    "to_ea": "0x996323",
    "to_name": "",
    "type": 21
  },
  {
    "from_ea": "0x996323",
    "to_ea": "0x996324",
    "to_name": "",
    "type": 21
  },
  {
    "from_ea": "0x996324",
    "to_ea": "0x99632A",
    "to_name": "",
    "type": 21
  },
  {
    "from_ea": "0x996324",
    "to_ea": "0xB312BC",
    "to_name": "off_B312BC",
    "type": 3
  },
  {
    "from_ea": "0x99632A",
    "to_ea": "0x98BEEB",
    "to_name": "__decode_pointer",
    "type": 17
  },
  {
    "from_ea": "0x99632A",
    "to_ea": "0x99632F",
    "to_name": "",
    "type": 21
  },
  {
    "from_ea": "0x99632F",
    "to_ea": "0x996330",
    "to_name": "",
    "type": 21
  },
  {
    "from_ea": "0x996330",
    "to_ea": "0x996332",
    "to_name": "",
    "type": 21
  },
  {
    "from_ea": "0x996332",
    "to_ea": "0x996335",
    "to_name": "",
    "type": 21
  },
  {
    "from_ea": "0x996335",
    "to_ea": "0x99688D",
    "to_name": "loc_99688D",
    "type": 19
  }
]