[
  {
    "from_ea": "0x5E0D40",
    "to_ea": "0x5E0D43",
    "to_name": "",
    "type": 21
  },
  {
    "from_ea": "0x5E0D43",
    "to_ea": "0x5E0D44",
    "to_name": "",
    "type": 21
  },
  {
    "from_ea": "0x5E0D44",
    "to_ea": "0x5E0D46",
    "to_name": "",
    "type": 21
  },
  {
    "from_ea": "0x5E0D46",
    "to_ea": "0x5E0D48",
    "to_name": "",
    "type": 21
  },
  {
    "from_ea": "0x5E0D48",
    "to_ea": "0x5E0D4E",
    "to_name": "",
    "type": 21
  },
  {
    "from_ea": "0x5E0D4E",
    "to_ea": "0x5E0D50",
    "to_name": "",
    "type": 21
  },
  {
    "from_ea": "0x5E0D50",
    "to_ea": "0x5E0D52",
    "to_name": "",
    "type": 21
  },
  {
    "from_ea": "0x5E0D52",
    "to_ea": "0x5E0D53",
    "to_name": "",
    "type": 21
  },
  {
    "from_ea": "0x5E0D53",
    "to_ea": "0x5E0D56",
    "to_name": "",
    "type": 21
  },
  {
    "from_ea": "0x5E0D56",
    "to_ea": "0x547ED0",
    "to_name": "Calc_ActorBaseEncumbrance",
    "type": 17
  },
  {
    "from_ea": "0x5E0D56",
    "to_ea": "0x5E0D5B",
    "to_name": "",
    "type": 21
  },
  {
    "from_ea": "0x5E0D5B",
    "to_ea": "0x5E0D5D",
    "to_name": "",
    "type": 21
  },
  {
    "from_ea": "0x5E0D5D",
    "to_ea": "0x5E0D61",
    "to_name": "",
    "type": 21
  },
  {
    "from_ea": "0x5E0D61",
    "to_ea": "0x5E0D67",
    "to_name": "",
    "type": 21
  },
  {
    "from_ea": "0x5E0D67",
    "to_ea": "0x5E0D6A",
    "to_name": "",
    "type": 21
  },
  {
    "from_ea": "0x5E0D6A",
    "to_ea": "0x5E0D6C",
    "to_name": "",
    "type": 21
  },
  {
    "from_ea": "0x5E0D6C",
    "to_ea": "0x5E0D6E",
    "to_name": "",
    "type": 21
  },
  {
    "from_ea": "0x5E0D6E",
    "to_ea": "0x5E0D70",
    "to_name": "",
    "type": 21
  },
  {
    "from_ea": "0x5E0D70",
    "to_ea": "0x5E0D74",
    "to_name": "",
    "type": 21
  },
  {
    "from_ea": "0x5E0D74",
    "to_ea": "0x5E0D78",
    "to_name": "",
    "type": 21
  },
  {
    "from_ea": "0x5E0D78",
    "to_ea": "0x5E0D79",
    "to_name": "",
    "type": 21
  },
  {
    "from_ea": "0x5E0D79",
    "to_ea": "0x5E0D7D",
    "to_name": "",
    "type": 21
  },
  {
    "from_ea": "0x5E0D7D",
    "to_ea": "0x5E0D7F",
    "to_name": "",
    "type": 21
  },
  {
    "from_ea": "0x5E0D7F",
    "to_ea": "0x5E0D81",
    "to_name": "",
    "type": 21
  },
  {
    "from_ea": "0x5E0D81",
    "to_ea": "0x5E0D84",
    "to_name": "",
    "type": 21
  },
  {
    "from_ea": "0x5E0D84",
    "to_ea": "0x5E0D86",
    "to_name": "",
    "type": 21
  },
  {
    "from_ea": "0x5E0D84",
    "to_ea": "0x5E0D8F",
    "to_name": "loc_5E0D8F",
    "type": 19
  },
  {
    "from_ea": "0x5E0D86",
    "to_ea": "0x5E0D8B",
    "to_name": "",
    "type": 21
  },
  {
    "from_ea": "0x5E0D8B",
    "to_ea": "0x5E0D8E",
    "to_name": "",
    "type": 21
  },
  {
    "from_ea": "0x5E0D8F",
    "to_ea": "0x5E0D91",
    "to_name": "",
    "type": 21
  },
  {
    "from_ea": "0x5E0D91",
    "to_ea": "0x5E0D94",
    "to_name": "",
    "type": 21
  }
]