{
  "callees_count": 12,
  "callers_count": 0,
  "comment_regular": "",
  "comment_repeatable": "",
  "data_refs_count": 0,
  "display_name": "EquippedWeaponData_GetDamage:::WeaponDamage",
  "end_ea": "0x485089",
  "flags": 21504,
  "has_pseudocode": true,
  "name": "EquippedWeaponData_GetDamage:::WeaponDamage",
  "segment": ".text",
  "sha256": "4468f2706c43844abe805ba42f7f923cd04a57a1a64fc6e8808e59a43a839272",
  "size": 229,
  "start_ea": "0x484FA4",
  "type": "void __usercall(int@<ebx>, int@<ebp>, Actor *@<esi>, double@<st0>, int, int, float, double, float, float, int, float, float, float)",
  "xrefs_from_count": 81,
  "xrefs_to_count": 1
}