[
  {
    "from_ea": "0x4049B2",
    "from_name": "",
    "to_ea": "0x982D71",
    "type": 17
  },
  {
    "from_ea": "0x40E1B6",
    "from_name": "",
    "to_ea": "0x982D71",
    "type": 17
  },
  {
    "from_ea": "0x42E414",
    "from_name": "",
    "to_ea": "0x982D71",
    "type": 17
  },
  {
    "from_ea": "0x4300D6",
    "from_name": "",
    "to_ea": "0x982D71",
    "type": 17
  },
  {
    "from_ea": "0x430A30",
    "from_name": "",
    "to_ea": "0x982D71",
    "type": 17
  },
  {
    "from_ea": "0x431857",
    "from_name": "",
    "to_ea": "0x982D71",
    "type": 17
  },
  {
    "from_ea": "0x431911",
    "from_name": "",
    "to_ea": "0x982D71",
    "type": 17
  },
  {
    "from_ea": "0x6AB2FB",
    "from_name": "",
    "to_ea": "0x982D71",
    "type": 17
  },
  {
    "from_ea": "0x6ACED9",
    "from_name": "",
    "to_ea": "0x982D71",
    "type": 17
  },
  {
    "from_ea": "0x6AD1AB",
    "from_name": "",
    "to_ea": "0x982D71",
    "type": 17
  },
  {
    "from_ea": "0x6AD491",
    "from_name": "",
    "to_ea": "0x982D71",
    "type": 17
  },
  {
    "from_ea": "0x6AD79B",
    "from_name": "",
    "to_ea": "0x982D71",
    "type": 17
  },
  {
    "from_ea": "0x6ADB0A",
    "from_name": "",
    "to_ea": "0x982D71",
    "type": 17
  },
  {
    "from_ea": "0x6ADCEF",
    "from_name": "",
    "to_ea": "0x982D71",
    "type": 17
  }
]