[
  {
    "from_ea": "0x519CE0",
    "to_ea": "0x519CE4",
    "to_name": "",
    "type": 21
  },
  {
    "from_ea": "0x519CE4",
    "to_ea": "0x519CE6",
    "to_name": "",
    "type": 21
  },
  {
    "from_ea": "0x519CE4",
    "to_ea": "0x519CEF",
    "to_name": "loc_519CEF",
    "type": 19
  },
  {
    "from_ea": "0x519CE6",
    "to_ea": "0x519CE9",
    "to_name": "",
    "type": 21
  },
  {
    "from_ea": "0x519CE9",
    "to_ea": "0x519CEC",
    "to_name": "",
    "type": 21
  },
  {
    "from_ea": "0x519CEC",
    "to_ea": "0x519CEE",
    "to_name": "",
    "type": 21
  },
  {
    "from_ea": "0x519CEF",
    "to_ea": "0x519CF1",
    "to_name": "",
    "type": 21
  }
]